ocr4all_helper_scripts/__init__.py
ocr4all_helper_scripts/cli/__init__.py
ocr4all_helper_scripts/cli/legacyconvert.py
ocr4all_helper_scripts/cli/pagelineseg.py
ocr4all_helper_scripts/cli/skewestimate.py
ocr4all_helper_scripts/helpers/__init__.py
ocr4all_helper_scripts/helpers/legacyconvert_helper.py
ocr4all_helper_scripts/helpers/pagedir2pagexml_helper.py
ocr4all_helper_scripts/helpers/pagelineseg_helper.py
ocr4all_helper_scripts/helpers/skewestimate_helper.py
ocr4all_helper_scripts/lib/__init__.py
ocr4all_helper_scripts/lib/imgmanipulate.py
ocr4all_helper_scripts/lib/morph.py
ocr4all_helper_scripts/lib/nlbin.py
ocr4all_helper_scripts/lib/pseg.py
ocr4all_helper_scripts/lib/sl.py
ocr4all_helper_scripts/test/__init__.py
ocr4all_helper_scripts/test/test_pagelineseg.py
ocr4all_helper_scripts/tests/__init__.py
ocr4all_helper_scripts/utils/__init__.py
ocr4all_helper_scripts/utils/datastructures.py
ocr4all_helper_scripts/utils/imageutils.py
ocr4all_helper_scripts/utils/pageutils.py
ocr4all_helper_scripts-0.4.1.dist-info/LICENSE
ocr4all_helper_scripts-0.4.1.dist-info/METADATA
ocr4all_helper_scripts-0.4.1.dist-info/WHEEL
ocr4all_helper_scripts-0.4.1.dist-info/entry_points.txt
ocr4all_helper_scripts-0.4.1.dist-info/top_level.txt
ocr4all_helper_scripts-0.4.1.dist-info/RECORD
