Metadata-Version: 2.1
Name: ocr4all-helper-scripts
Version: 0.4.1
Summary: Different python scripts used in the OCR4all workflow.
Home-page: https://github.com/OCR4all/OCR4all_helper-scripts
Author: Nico Balbach, Maximilian Nöth
Author-email: nico.balbach@informatik.uni-wuerzburg.de, maximilian.noeth@uni-wuerzburg.de
License: MIT License
Keywords: OCR,optical character recognition
Platform: UNKNOWN
Classifier: Programming Language :: Python :: 3
Classifier: License :: OSI Approved :: MIT License
Classifier: Operating System :: OS Independent
License-File: LICENSE
Requires-Dist: click
Requires-Dist: numpy
Requires-Dist: lxml
Requires-Dist: scikit-image
Requires-Dist: Pillow
